solana_toolbox/__init__.py
solana_toolbox/features/jupiter.py
solana_toolbox-0.1.0.dist-info/METADATA
solana_toolbox-0.1.0.dist-info/WHEEL
solana_toolbox-0.1.0.dist-info/RECORD
