Metadata-Version: 2.1
Name: solana-toolbox
Version: 0.1.0
Summary: 
Author: Victor
Author-email: vector.code11@gmail.com
Requires-Python: >=3.12,<4.0
Classifier: Programming Language :: Python :: 3
Classifier: Programming Language :: Python :: 3.12
Classifier: Programming Language :: Python :: 3.13
Requires-Dist: asyncstdlib (>=3.13.0,<4.0.0)
Requires-Dist: httpx (>=0.28.1,<0.29.0)
Requires-Dist: solana (>=0.36.1,<0.37.0)
Requires-Dist: solders (>=0.23.0,<0.24.0)
